[
  {
    "slug": "introduction-to-antibiotics",
    "title": "Introduction",
    "fullPath": "lessons/year2/pharmacology/introduction-to-antibiotics.md",
    "pathParts": [
      "year2",
      "pharmacology",
      "introduction-to-antibiotics.md"
    ]
  },
  {
    "slug": "anemia",
    "title": "Anemia",
    "fullPath": "lessons/year5/pediatrics/anemia.md",
    "pathParts": [
      "year5",
      "pediatrics",
      "anemia.md"
    ]
  },
  {
    "slug": "vsd-diagnosis",
    "title": "Diagnosis",
    "fullPath": "lessons/year5/pediatrics/cardiology/vsd/diagnosis.md",
    "pathParts": [
      "year5",
      "pediatrics",
      "cardiology",
      "vsd",
      "diagnosis.md"
    ]
  },
  {
    "slug": "vsd",
    "title": "Ventricular",
    "fullPath": "lessons/year5/pediatrics/vsd.md",
    "pathParts": [
      "year5",
      "pediatrics",
      "vsd.md"
    ]
  }
]